fast_wave/__init__.py
fast_wave/caching.py
fast_wave/wavefunction_cython.cp310-win_amd64.pyd
fast_wave/wavefunction_cython.cp311-win_amd64.pyd
fast_wave/wavefunction_cython.cp312-win_amd64.pyd
fast_wave/wavefunction_cython.cpython-310-x86_64-linux-gnu.so
fast_wave/wavefunction_cython.cpython-311-x86_64-linux-gnu.so
fast_wave/wavefunction_cython.cpython-312-x86_64-linux-gnu.so
fast_wave/wavefunction_cython.pyx
fast_wave/wavefunction_mpmath.py
fast_wave/wavefunction_numba.py
fast_wave-1.6.9.dist-info/LICENSE
fast_wave-1.6.9.dist-info/METADATA
fast_wave-1.6.9.dist-info/NOTICE.txt
fast_wave-1.6.9.dist-info/WHEEL
fast_wave-1.6.9.dist-info/top_level.txt
fast_wave-1.6.9.dist-info/RECORD
