Metadata-Version: 2.1
Name: fast_wave
Version: 1.6.9
Summary: Package for the calculation of the time-independent wavefunction.
Home-page: https://github.com/pikachu123deimos/fast-wave
Author: fast_wave
Author-email: matheusgomescord@gmail.com
Classifier: Programming Language :: Python :: 3.11
Classifier: Topic :: Scientific/Engineering :: Mathematics
Classifier: License :: OSI Approved :: BSD License
Classifier: Development Status :: 5 - Production/Stable
License-File: LICENSE
License-File: NOTICE.txt
Requires-Dist: llvmlite ==0.42.0
Requires-Dist: mpmath ==1.3.0
Requires-Dist: numba ==0.59.1
Requires-Dist: numpy ==1.26.4
Requires-Dist: sympy ==1.12
Requires-Dist: cython ==3.0.10
